cloudfront_signed_cookies/__about__.py
cloudfront_signed_cookies/__init__.py
cloudfront_signed_cookies/__main__.py
cloudfront_signed_cookies/errors.py
cloudfront_signed_cookies/signer.py
cloudfront_signed_cookies/cli/__init__.py
cloudfront_signed_cookies/cli/genkeys/__init__.py
cloudfront_signed_cookies/cli/sign/__init__.py
cloudfront_signed_cookies-1.2.dist-info/METADATA
cloudfront_signed_cookies-1.2.dist-info/WHEEL
cloudfront_signed_cookies-1.2.dist-info/licenses/LICENSE.txt
cloudfront_signed_cookies-1.2.dist-info/RECORD
