Metadata-Version: 2.1
Name: cloudfront-signed-cookies
Version: 1.2
Summary: A Python package for controlling access to content sitting behind a CloudFront distribution using signed cookies.
Project-URL: Documentation, https://github.com/unknown/cloudfront-signed-cookies#readme
Project-URL: Source, https://github.com/bin3xish477/cloudfront-signed-cookies
Author-email: Alexis Rodriguez <arodriguez99@protonmail.com>
License-Expression: MIT
License-File: LICENSE.txt
Classifier: Development Status :: 4 - Beta
Classifier: Programming Language :: Python
Classifier: Programming Language :: Python :: 3.7
Classifier: Programming Language :: Python :: 3.8
Classifier: Programming Language :: Python :: 3.9
Classifier: Programming Language :: Python :: 3.10
Classifier: Programming Language :: Python :: 3.11
Classifier: Programming Language :: Python :: Implementation :: CPython
Classifier: Programming Language :: Python :: Implementation :: PyPy
Requires-Python: >=3.7
Requires-Dist: click>=8.1.3
Requires-Dist: cryptography>=38.0.4
